MANIFEST.in
VERSION
setup.py
aegisx.ext.pki.egg-info/PKG-INFO
aegisx.ext.pki.egg-info/SOURCES.txt
aegisx.ext.pki.egg-info/dependency_links.txt
aegisx.ext.pki.egg-info/entry_points.txt
aegisx.ext.pki.egg-info/requires.txt
aegisx.ext.pki.egg-info/top_level.txt
aegisx/ext/pki/package.json
aegisx/ext/pki/cli/__init__.py
aegisx/ext/pki/cli/const.py